engfmt.py
engfmt-1.2.0.dist-info/LICENSE
engfmt-1.2.0.dist-info/METADATA
engfmt-1.2.0.dist-info/WHEEL
engfmt-1.2.0.dist-info/top_level.txt
engfmt-1.2.0.dist-info/zip-safe
engfmt-1.2.0.dist-info/RECORD
