Metadata-Version: 2.1
Name: engfmt
Version: 1.2.0
Summary: read and write in engineering notation
Home-page: http://nurdletech.com/linux-utilities/engfmt
Author: Ken Kundert
Author-email: engfmt@nurdletech.com
License: GPLv3+
Download-URL: https://github.com/kenkundert/engfmt/tarball/master
Keywords: quantities,engfmt,engineering,notation,SI,scale factors
Platform: UNKNOWN
Classifier: Development Status :: 6 - Mature
Classifier: Intended Audience :: Developers
Classifier: Intended Audience :: Science/Research
Classifier: License :: OSI Approved :: GNU General Public License v3 or later (GPLv3+)
Classifier: Natural Language :: English
Classifier: Operating System :: POSIX :: Linux
Classifier: Programming Language :: Python :: 2.7
Classifier: Programming Language :: Python :: 3.3
Classifier: Programming Language :: Python :: 3.4
Classifier: Programming Language :: Python :: 3.5
Classifier: Programming Language :: Python :: 3.6
Classifier: Topic :: Utilities
Classifier: Topic :: Scientific/Engineering
Requires-Dist: six
